pre_process_chain/__init__.py
pre_process_chain/pre_process_chain.py
pre_process_chain/text_process.py
pre_process_chain/dd/__init__.py
pre_process_chain/dd/chinese_digits.py
pre_process_chain/dd/frequent_chars.py
pre_process_chain/dd/symbol_convert.py
text_pre_process/__init__.py
text_pre_process/pre_process_chain.py
text_pre_process/text_process.py
text_pre_process/dd/__init__.py
text_pre_process/dd/chinese_digits.py
text_pre_process/dd/frequent_chars.py
text_pre_process/dd/symbol_convert.py
pre_process_chain-0.1.4.dist-info/METADATA
pre_process_chain-0.1.4.dist-info/WHEEL
pre_process_chain-0.1.4.dist-info/top_level.txt
pre_process_chain-0.1.4.dist-info/RECORD
