Metadata-Version: 2.1
Name: pre_process_chain
Version: 0.1.4
Summary: 包含一种链式预处理设计模式（以更低的时间成本解决同时需要多种预处理方式的场景）、以及实现了一些文本预处理方法的包
Home-page: 
Author: ray.ping
Author-email: 342099577@qq.com
License: MIT
Requires-Dist: cn2an >=0.5.22
